{
  "version": 1,
  "updatedAt": "2026-06-23T12:54:02.098876Z",
  "questions": [
    {
      "id": "riddle_alligator_very_hard_001",
      "type": "riddle",
      "level": "very_hard",
      "category": "animals",
      "active": true,
      "answerId": "alligator",
      "promptEn": "I am a large reptile. I live near rivers and swamps. My body has scales. I have a wide snout and strong jaws. What am I?",
      "hintJp": "大きな はちゅうるい。川や沼の近くにすみ、口先が広い。",
      "choices": [
        "alligator",
        "penguin",
        "rabbit",
        "lion"
      ]
    },
    {
      "id": "riddle_penguin_very_hard_002",
      "type": "riddle",
      "level": "very_hard",
      "category": "animals",
      "active": true,
      "answerId": "penguin",
      "promptEn": "I am a bird, but I do not fly. I swim very well and live in cold places. I have black and white feathers. What am I?",
      "hintJp": "鳥だけど飛ばない。泳ぎが得意で、黒と白の羽がある。",
      "choices": [
        "penguin",
        "fish",
        "elephant",
        "cat"
      ]
    },
    {
      "id": "riddle_elephant_very_hard_003",
      "type": "riddle",
      "level": "very_hard",
      "category": "animals",
      "active": true,
      "answerId": "elephant",
      "promptEn": "I am the largest land animal. I have big ears and a long trunk. I can use my nose like a hand. What am I?",
      "hintJp": "陸の上でとても大きい動物。大きな耳と長い鼻がある。",
      "choices": [
        "elephant",
        "rabbit",
        "bird",
        "fish"
      ]
    },
    {
      "id": "riddle_rabbit_very_hard_004",
      "type": "riddle",
      "level": "very_hard",
      "category": "animals",
      "active": true,
      "answerId": "rabbit",
      "promptEn": "I am small and soft. I have long ears and strong back legs. I often hop instead of walk. What am I?",
      "hintJp": "小さくてやわらかい。長い耳があり、ぴょんぴょん跳ねる。",
      "choices": [
        "rabbit",
        "alligator",
        "penguin",
        "bear"
      ]
    },
    {
      "id": "riddle_lion_very_hard_005",
      "type": "riddle",
      "level": "very_hard",
      "category": "animals",
      "active": true,
      "answerId": "lion",
      "promptEn": "I am a big cat. I have a loud roar. A male has a mane around his face. What am I?",
      "hintJp": "大きなネコの仲間。大きな声でほえ、たてがみがある。",
      "choices": [
        "lion",
        "rabbit",
        "fish",
        "penguin"
      ]
    },
    {
      "id": "riddle_fish_very_hard_006",
      "type": "riddle",
      "level": "very_hard",
      "category": "animals",
      "active": true,
      "answerId": "fish",
      "promptEn": "I live in water all the time. I breathe with gills. I use fins to move. What am I?",
      "hintJp": "水の中にすみ、えらで息をして、ひれで動く。",
      "choices": [
        "fish",
        "bird",
        "cat",
        "elephant"
      ]
    },
    {
      "id": "riddle_bird_very_hard_007",
      "type": "riddle",
      "level": "very_hard",
      "category": "animals",
      "active": true,
      "answerId": "bird",
      "promptEn": "I have feathers and wings. Many of my kind can fly. I may build a nest in a tree. What am I?",
      "hintJp": "羽と翼があり、多くは飛べる。木に巣を作ることがある。",
      "choices": [
        "bird",
        "fish",
        "alligator",
        "rabbit"
      ]
    },
    {
      "id": "riddle_bear_very_hard_008",
      "type": "riddle",
      "level": "very_hard",
      "category": "animals",
      "active": true,
      "answerId": "bear",
      "promptEn": "I am large and strong. I have thick fur. Some of my kind sleep through much of winter. What am I?",
      "hintJp": "大きくて強く、厚い毛がある。冬に長く眠る仲間もいる。",
      "choices": [
        "bear",
        "cat",
        "bird",
        "fish"
      ]
    },
    {
      "id": "riddle_cat_very_hard_009",
      "type": "riddle",
      "level": "very_hard",
      "category": "animals",
      "active": true,
      "answerId": "cat",
      "promptEn": "I am a small pet. I can climb and I often say meow. I may chase a toy mouse. What am I?",
      "hintJp": "小さなペット。登るのが得意で、ニャーと鳴く。",
      "choices": [
        "cat",
        "dog",
        "fish",
        "elephant"
      ]
    },
    {
      "id": "riddle_dog_very_hard_010",
      "type": "riddle",
      "level": "very_hard",
      "category": "animals",
      "active": true,
      "answerId": "dog",
      "promptEn": "I am a friendly pet. I may bark when someone comes to the door. People often take me for walks. What am I?",
      "hintJp": "人となかよくするペット。ワンと鳴き、散歩に行くことが多い。",
      "choices": [
        "dog",
        "cat",
        "penguin",
        "alligator"
      ]
    },
    {
      "id": "listening_alligator_very_hard_001",
      "type": "listening",
      "level": "very_hard",
      "category": "animals",
      "active": true,
      "answerId": "alligator",
      "storyEn": "A child sees an animal resting near the water. It has short legs, scales, and a powerful tail. Its mouth is wide and full of sharp teeth.",
      "questionEn": "Which animal is resting near the water?",
      "hintJp": "水辺にいて、短い足、うろこ、強い尾、広い口を持つ動物。",
      "choices": [
        "alligator",
        "rabbit",
        "bird",
        "penguin"
      ]
    },
    {
      "id": "listening_penguin_very_hard_002",
      "type": "listening",
      "level": "very_hard",
      "category": "animals",
      "active": true,
      "answerId": "penguin",
      "storyEn": "The animal cannot fly, even though it is a bird. It slides on ice and swims quickly in the sea. Its body is black and white.",
      "questionEn": "Which bird is described?",
      "hintJp": "鳥だけど飛ばず、氷の上をすべり、海で泳ぐ。",
      "choices": [
        "penguin",
        "bird",
        "cat",
        "lion"
      ]
    },
    {
      "id": "listening_elephant_very_hard_003",
      "type": "listening",
      "level": "very_hard",
      "category": "animals",
      "active": true,
      "answerId": "elephant",
      "storyEn": "The animal walks slowly across the grassland. It uses a long trunk to pick up food and water. Its ears are very large.",
      "questionEn": "Which animal uses a trunk?",
      "hintJp": "長い鼻で食べ物や水を取る、大きな耳の動物。",
      "choices": [
        "elephant",
        "bear",
        "dog",
        "fish"
      ]
    },
    {
      "id": "listening_rabbit_very_hard_004",
      "type": "listening",
      "level": "very_hard",
      "category": "animals",
      "active": true,
      "answerId": "rabbit",
      "storyEn": "The animal hears a sound and quickly hops away. Its ears are long, and its body is small and soft.",
      "questionEn": "Which animal hops away?",
      "hintJp": "長い耳があり、音を聞いて跳ねて逃げる小さな動物。",
      "choices": [
        "rabbit",
        "alligator",
        "elephant",
        "penguin"
      ]
    },
    {
      "id": "listening_lion_very_hard_005",
      "type": "listening",
      "level": "very_hard",
      "category": "animals",
      "active": true,
      "answerId": "lion",
      "storyEn": "The animal stands in the sun and gives a loud roar. Other animals move away because it is a strong hunter.",
      "questionEn": "Which animal roars loudly?",
      "hintJp": "大きくほえ、強いハンターである動物。",
      "choices": [
        "lion",
        "fish",
        "rabbit",
        "cat"
      ]
    },
    {
      "id": "listening_fish_very_hard_006",
      "type": "listening",
      "level": "very_hard",
      "category": "animals",
      "active": true,
      "answerId": "fish",
      "storyEn": "The animal does not walk on land. It moves with fins and lives under the water.",
      "questionEn": "Which animal lives under the water?",
      "hintJp": "陸を歩かず、水中でひれを使って動く。",
      "choices": [
        "fish",
        "bird",
        "dog",
        "bear"
      ]
    },
    {
      "id": "listening_bird_very_hard_007",
      "type": "listening",
      "level": "very_hard",
      "category": "animals",
      "active": true,
      "answerId": "bird",
      "storyEn": "The animal sits on a branch. It has feathers, a beak, and wings. Soon it flies to another tree.",
      "questionEn": "Which animal flies to another tree?",
      "hintJp": "枝にとまり、羽・くちばし・翼があり、別の木へ飛ぶ。",
      "choices": [
        "bird",
        "fish",
        "alligator",
        "rabbit"
      ]
    },
    {
      "id": "listening_bear_very_hard_008",
      "type": "listening",
      "level": "very_hard",
      "category": "animals",
      "active": true,
      "answerId": "bear",
      "storyEn": "The animal is heavy and covered with thick fur. It walks through the forest looking for food before winter.",
      "questionEn": "Which animal has thick fur and looks for food before winter?",
      "hintJp": "厚い毛があり、冬の前に森で食べ物を探す。",
      "choices": [
        "bear",
        "penguin",
        "fish",
        "cat"
      ]
    },
    {
      "id": "listening_cat_very_hard_009",
      "type": "listening",
      "level": "very_hard",
      "category": "animals",
      "active": true,
      "answerId": "cat",
      "storyEn": "The animal jumps onto the sofa and curls up to sleep. When it wants food, it says meow.",
      "questionEn": "Which animal says meow?",
      "hintJp": "ソファに乗って丸くなり、ニャーと鳴くペット。",
      "choices": [
        "cat",
        "dog",
        "lion",
        "elephant"
      ]
    },
    {
      "id": "listening_dog_very_hard_010",
      "type": "listening",
      "level": "very_hard",
      "category": "animals",
      "active": true,
      "answerId": "dog",
      "storyEn": "The animal runs to the door when it hears a knock. It barks and wags its tail.",
      "questionEn": "Which animal barks and wags its tail?",
      "hintJp": "ノックの音でドアへ走り、ワンと鳴いてしっぽを振る。",
      "choices": [
        "dog",
        "cat",
        "fish",
        "rabbit"
      ]
    }
  ]
}
